nwscript_language_server/__init__.py
nwscript_language_server/cli.py
nwscript_language_server/py.typed
nwscript_language_server/server.py
nwscript_language_server-0.3.0.dist-info/LICENSE
nwscript_language_server-0.3.0.dist-info/METADATA
nwscript_language_server-0.3.0.dist-info/WHEEL
nwscript_language_server-0.3.0.dist-info/entry_points.txt
nwscript_language_server-0.3.0.dist-info/RECORD
