Metadata-Version: 2.1
Name: nwscript-language-server
Version: 0.3.0
Summary: A language server for Bioware's nwscript
Home-page: https://github.com/jd28/nwscript-lsp
Keywords: nwscript,completion,lsp,language-server-protocol
Author: jmd
Author-email: joshua.m.dean@gmail.com
Requires-Python: >=3.10,<4.0
Classifier: Programming Language :: Python :: 3
Classifier: Programming Language :: Python :: 3.10
Classifier: Programming Language :: Python :: 3.11
Classifier: Programming Language :: Python :: 3.12
Requires-Dist: cattrs (>=23.1.2)
Requires-Dist: docstring-to-markdown (==0.*)
Requires-Dist: lsprotocol (>=2022.0.0a9)
Requires-Dist: pygls (>=1.1.0,<2.0.0)
Requires-Dist: rollnw (==0.21.*)
Project-URL: Repository, https://github.com/jd28/nwscript-lsp
